iot_outlier_src/__init__.py
iot_outlier_src/_config.py
iot_outlier_src/main_featcomp-class.py
iot_outlier_src/data_process/__init__.py
iot_outlier_src/data_process/data.py
iot_outlier_src/data_process/data_factory.py
iot_outlier_src/data_process/parse_subflows.py
iot_outlier_src/data_process/pcap.py
iot_outlier_src/data_process/pcap2features_sampling.py
iot_outlier_src/detector/__init__.py
iot_outlier_src/detector/ae_class.py
iot_outlier_src/detector/detector_factory.py
iot_outlier_src/detector/gmm_class.py
iot_outlier_src/detector/kde_class.py
iot_outlier_src/detector/ocsvm_class.py
iot_outlier_src/detector/pca_class.py
iot_outlier_src/detector/base/__init__.py
iot_outlier_src/detector/base/base_detector.py
iot_outlier_src/detector/base/gmm_base.py
iot_outlier_src/detector/initialize/__init__.py
iot_outlier_src/detector/initialize/diagonalize.py
iot_outlier_src/detector/initialize/quickshift/__init__.py
iot_outlier_src/detector/initialize/quickshift/setup.py
iot_outlier_src/detector/model_selection/__init__.py
iot_outlier_src/detector/model_selection/grid_search.py
iot_outlier_src/legacy/__init__.py
iot_outlier_src/legacy/data_factory-20191126.py
iot_outlier_src/legacy/dataset-backup.py
iot_outlier_src/legacy/demo.py
iot_outlier_src/legacy/experiment_class.py
iot_outlier_src/legacy/experiment_class_meanshift_20191020.py
iot_outlier_src/legacy/gmm_base_my_own.py
iot_outlier_src/legacy/gmm_class_backup.py
iot_outlier_src/legacy/isoforest_class.py
iot_outlier_src/legacy/main_feat_comp_gridsearch.py
iot_outlier_src/legacy/main_feat_comp_mixed_gridsearch.py
iot_outlier_src/legacy/main_featcomp-class.py
iot_outlier_src/legacy/main_featcomp-class3.py
iot_outlier_src/legacy/main_featcomp-sampling-more.py
iot_outlier_src/legacy/main_featcomp.py
iot_outlier_src/legacy/main_featcomp_sampling.py
iot_outlier_src/legacy/main_featcomp_sampling_20191028.py
iot_outlier_src/legacy/main_featcomp_sampling_20191112.py
iot_outlier_src/legacy/main_features_comparison.py
iotoutlier1-0.0.1.dist-info/LICENSE
iotoutlier1-0.0.1.dist-info/METADATA
iotoutlier1-0.0.1.dist-info/WHEEL
iotoutlier1-0.0.1.dist-info/top_level.txt
iotoutlier1-0.0.1.dist-info/RECORD
