Metadata-Version: 2.1
Name: iotoutlier1
Version: 0.0.1
Summary: Data representation for IoT traffic
Home-page: https://github.com/Learn-Live/IoT_feature_sets_comparison
Author: Kun
Author-email: kun.bj@outlook.com
License: xxx
Download-URL: https://github.com/Learn-Live/IoT_feature_sets_comparison
Platform: UNKNOWN
Classifier: Development Status :: 5 - Production/Stable
Classifier: Intended Audience :: Developers
Classifier: Intended Audience :: Education
Classifier: Intended Audience :: Science/Research
Classifier: Programming Language :: Python :: 3
Classifier: Programming Language :: Python :: 3.7
Classifier: Topic :: Software Development :: Libraries
Classifier: Topic :: Software Development :: Libraries :: Python Modules
Requires-Python: >=3.6
Requires-Dist: numpy (>=1.17.0)
Requires-Dist: scipy (>=1.3.1)
Requires-Dist: pandas (>=0.25.1)
Requires-Dist: pyod (>=0.7.4)
Requires-Dist: scapy (>=2.4.3)
Requires-Dist: scikit-learn (>=0.21.3)
Requires-Dist: tensorflow
Requires-Dist: tensorboard
Requires-Dist: keras
Provides-Extra: terminal
Requires-Dist: colorama ; extra == 'terminal'
Provides-Extra: tests
Requires-Dist: pytest ; extra == 'tests'
Requires-Dist: requests ; extra == 'tests'
Requires-Dist: markdown ; extra == 'tests'
Provides-Extra: visualize
Requires-Dist: matplotlib (>=3.3.1) ; extra == 'visualize'
